redsys/__init__.py
redsys-0.3.0.dist-info/METADATA
redsys-0.3.0.dist-info/WHEEL
redsys-0.3.0.dist-info/top_level.txt
redsys-0.3.0.dist-info/RECORD
