Metadata-Version: 2.4
Name: redsys
Version: 0.3.0
Summary: A client to submit payment orders to the Redsys service.
Home-page: http://www.zikzakmedia.com
Download-URL: https://github.com/nanticzz/python-redsys
Author: Zikzakmedia SL
Author-email: zikzak@zikzakmedia.com
License: General Public Licence 2
Provides: redsys
Requires-Dist: pycryptodome
Dynamic: author
Dynamic: author-email
Dynamic: download-url
Dynamic: home-page
Dynamic: license
Dynamic: provides
Dynamic: requires-dist
Dynamic: summary
